tickerdax/__init__.py
tickerdax/__main__.py
tickerdax/app.py
tickerdax/cli.py
tickerdax/client.py
tickerdax/config_base.py
tickerdax/constants.py
tickerdax/downloader.py
tickerdax/example_configs/config.json
tickerdax/example_configs/config.yaml
tickerdax/formatting.py
tickerdax/streamer.py
tickerdax-0.0.83.dist-info/LICENSE
tickerdax-0.0.83.dist-info/METADATA
tickerdax-0.0.83.dist-info/WHEEL
tickerdax-0.0.83.dist-info/entry_points.txt
tickerdax-0.0.83.dist-info/RECORD
