Metadata-Version: 2.1
Name: tickerdax
Version: 0.0.83
Summary: A python client for tickerdax.com with a built-in caching system.
Home-page: https://github.com/tickerdax/tickerdax-client
License: MIT
Author: tickerdax.com
Author-email: info@tickerdax.com
Requires-Python: >=3.7,<4.0.0
Classifier: License :: OSI Approved :: MIT License
Classifier: Operating System :: OS Independent
Classifier: Programming Language :: Python :: 3
Classifier: Programming Language :: Python :: 3.7
Classifier: Programming Language :: Python :: 3.8
Classifier: Programming Language :: Python :: 3.9
Classifier: Programming Language :: Python :: 3.10
Classifier: Programming Language :: Python :: 3.11
Requires-Dist: art (>=5.8,<6.0)
Requires-Dist: docker (>=6.0.1,<7.0.0)
Requires-Dist: fastapi (==0.*)
Requires-Dist: jinja2 (>=3.1.2,<4.0.0)
Requires-Dist: python-dateutil (>=2.8.2,<3.0.0)
Requires-Dist: python-dotenv (>=0.19.2,<0.20.0)
Requires-Dist: pyyaml (>=6.0,<7.0)
Requires-Dist: redis (>=4.1.4,<5.0.0)
Requires-Dist: schema (>=0.7.5,<0.8.0)
Requires-Dist: sentry-sdk (>=1.31.0)
Requires-Dist: tomlkit (>=0.11.6,<0.12.0)
Requires-Dist: typer[all] (>=0.7.0,<0.8.0)
Requires-Dist: uvicorn (==0.*)
Requires-Dist: websockets (>=10.4,<11.0) ; python_version == "3.10"
Requires-Dist: websockets (>=11.0.3,<12.0.0) ; python_version >= "3.11"
Requires-Dist: websockets (>=9.1.0,<10.0.0) ; python_version >= "3.7" and python_version < "3.10"
Project-URL: Bug Tracker, https://github.com/tickerdax/tickerdax-client/issues
Project-URL: Repository, https://github.com/tickerdax/tickerdax-client
